gpushare/__init__.py
gpushare/client.py
gpushare/exceptions.py
gpushare-0.1.11.dist-info/METADATA
gpushare-0.1.11.dist-info/WHEEL
gpushare-0.1.11.dist-info/top_level.txt
gpushare-0.1.11.dist-info/RECORD
